{
  "fileName": "story2",
  "count": 3,
  "section": [
    {
      "type": "nomal",
      "placeImage": "house",
      "script": [
        {
          "type": "word",
          "character": "휴",
          "leftImage": "hue",
          "rightImage": null,
          "count": 1,
          "speech": ["(더 살펴볼 곳이 있을까요?)"]
        },
        {
          "type": "word",
          "character": " ",
          "leftImage": null,
          "rightImage": null,
          "count": 1,
          "speech": ["(끼익)"]
        },
        {
          "type": "word",
          "character": "휴",
          "leftImage": "hue",
          "rightImage": null,
          "count": 1,
          "speech": ["...?"]
        }
      ]
    },
    {
      "type": "illustration",
      "placeImage": "04",
      "script": [
        {
          "type": "word",
          "character": null,
          "leftImage": null,
          "rightImage": null,
          "count": 0,
          "speech": [" "]
        }
      ]
    },
    {
      "type": "nomal",
      "placeImage": "house",
      "script": [
        {
          "type": "word",
          "character": "카르프",
          "leftImage": null,
          "rightImage": "karf",
          "count": 2,
          "speech": ["...", "휴?"]
        },
        {
          "type": "word",
          "character": "휴",
          "leftImage": "hue",
          "rightImage": null,
          "count": 2,
          "speech": ["!", "카르프!"]
        },
        {
          "type": "word",
          "character": "카르프",
          "leftImage": "hue",
          "rightImage": "karf",
          "count": 1,
          "speech": ["... 밖에 시끄럽던데 뭐하고 있던거야?"]
        },
        {
          "type": "word",
          "character": "휴",
          "leftImage": "hue",
          "rightImage": "karf",
          "count": 4,
          "speech": [
            "하하, 별일 아니었어요.",
            "그보다 카르프! 이번엔 방 안에 너무 오래 있었어요!",
            "무슨일 있던건 아니죠?",
            "오랫동안 나오지 않아서 정말 걱정했어요."
          ]
        },
        {
          "type": "word",
          "character": "카르프",
          "leftImage": "hue",
          "rightImage": "karf",
          "count": 5,
          "speech": [
            "...",
            "... 나...",
            "나가지 않았던건 연구 때문이였어.",
            "이번에는 조금 더 신경쓰다보니 그렇게 되었네...",
            "미안해 휴. 그렇다고 너를 이렇게 오랫동안 혼자 두지말아야했는데.",
            "그동안 별일 없었지?"
          ]
        },
        {
          "type": "word",
          "character": "휴",
          "leftImage": "hue",
          "rightImage": "karf",
          "count": 2,
          "speech": [
            "또 제가 말썽을 부렸을까봐 걱정하는거죠?",
            "걱정마세요. 이제 혼자서도 사고 치지않고 있을 수 있어요!"
          ]
        },
        {
          "type": "word",
          "character": "카르프",
          "leftImage": "hue",
          "rightImage": "karf",
          "count": 3,
          "speech": [
            "... 믿을께.",
            "...",
            "아니면 그동안 뭔가 기억나는거나 떠오르는건 있어?"
          ]
        },
        {
          "type": "word",
          "character": "휴",
          "leftImage": "hue",
          "rightImage": "karf",
          "count": 2,
          "speech": ["...", "아무것도요..."]
        },
        {
          "type": "word",
          "character": "카르프",
          "leftImage": "hue",
          "rightImage": "karf",
          "count": 2,
          "speech": ["...", "그렇구나 알았어."]
        },
        {
          "type": "word",
          "character": "휴",
          "leftImage": "hue",
          "rightImage": "karf",
          "count": 8,
          "speech": [
            "(카르프는 항상 저를 보면 같은 질문을 해요.)",
            "(이 질문이 무슨 의미인지 알아요.)",
            "(그 사람이 카르프에게 얼마나 소중한지도요.)",
            "(하지만 카르프...)",
            "...",
            "참,",
            "카르프, 방금전에 휠라가 저희에게 선물을 주고갔어요.",
            "크리스마스 선물이요!"
          ]
        },
        {
          "type": "word",
          "character": "카르프",
          "leftImage": "hue",
          "rightImage": "karf",
          "count": 1,
          "speech": ["...크리스마스?"]
        },
        {
          "type": "word",
          "character": "휴",
          "leftImage": "hue",
          "rightImage": "karf",
          "count": 4,
          "speech": [
            "네!",
            "카르프는 크리스마스를 알고 있었나요?",
            "저 크리스마스도 선물도 처음이라 너무 두근되어요.",
            "휠라가 크리스마스에 대해 알려주었는데, 눈을 반짝이면서 말하는데 정말 즐거워 보였어요."
          ]
        },
        {
          "type": "word",
          "character": "카르프",
          "leftImage": "hue",
          "rightImage": "karf",
          "count": 1,
          "speech": ["..."]
        },
        {
          "type": "word",
          "character": "휴",
          "leftImage": "hue",
          "rightImage": "karf",
          "count": 5,
          "speech": [
            "카르프는 크리스마스를 좋아하시나요?",
            "휠라가 말하기를 크리스마스는 모두가 행복해지는 파티라고 했어요.",
            "(그러고 보니 카르프에게도 크리스마스에 대해 물어보면 파티 준비에 도움이 될지 모르겠네요!)",
            "카르프도 매년 크리스마스를 기념했겠죠? 지금까지 어떤 크리스마스를 보내봤나요?",
            "카르프가 보내왔던 크리스마스 대해서도 알고 싶어요."
          ]
        },
        {
          "type": "word",
          "character": "카르프",
          "leftImage": "hue",
          "rightImage": "karf",
          "count": 7,
          "speech": [
            "내가 보냈던 크리스마스?",
            "...",
            "휠라가 어떻게 말했는지 자세히 모르겠지만...",
            "크리스마스를 보내는 방법은 지역마다 가문마다 사람마다 모두 달라.",
            "그러니까 반드시 모두가 행복한 날이 아닐 수 있다는 말이야.",
            "...나도 마찬가지고.",
            "너는 지금은 기억 못하지만 학교에서 크리스마스 파티가 열릴때마다 난 참가하지 않았잖아.",
            "휴, 나는 네가 기대할만한 크리스마스 이야기가 없어."
          ]
        },
        {
          "type": "word",
          "character": "휴",
          "leftImage": "hue",
          "rightImage": "karf",
          "count": 2,
          "speech": [
            "괜찮아요!",
            "그냥 카르프가보냈던 크리스마스가 궁금한거예요."
          ]
        },
        {
          "type": "word",
          "character": "카르프",
          "leftImage": "hue",
          "rightImage": "karf",
          "count": 1,
          "speech": ["모두 너무 따분하게 보내서 마땅히 말할 것도 없는걸..."]
        },
        {
          "type": "word",
          "character": "휴",
          "leftImage": "hue",
          "rightImage": "karf",
          "count": 2,
          "speech": [
            "정말 약간이라도 좋아요.",
            "크리스마스에 카르프가 어떻게보냈는지만 이야기해줘도 기쁠거예요."
          ]
        },
        {
          "type": "word",
          "character": "카르프",
          "leftImage": "hue",
          "rightImage": "karf",
          "count": 4,
          "speech": [
            "재미없게 보냈대도.",
            "...",
            "후우 알았어.",
            "이야기가 지루해도 난 몰라."
          ]
        },
        {
          "type": "word",
          "character": "휴",
          "leftImage": "hue",
          "rightImage": "karf",
          "count": 3,
          "speech": ["...!", "물론이죠!", "고마워요 카르프!"]
        },
        {
          "type": "word",
          "character": "카르프",
          "leftImage": "hue",
          "rightImage": "karf",
          "count": 3,
          "speech": [
            "...그러니까 내가 어렸을때 우리 가문에서는 크리스마스 파티를 매년 온 가족이 모여서 꽤 크게 열었어.",
            "나도 거기 참석해야했어.",
            "가문의 장자이기도 했고... 어머니 아버지가 준비하시는 자리라 나도 얼굴을 비춰야했거든."
          ]
        },
        {
          "type": "word",
          "character": "휴",
          "leftImage": "hue",
          "rightImage": "karf",
          "count": 2,
          "speech": [
            "휠라가 크리스마스는 소중한 사람과 보낸다고 했어요.",
            "카르프의 가문은 가족을 소중하게 생각했나봐요."
          ]
        },
        {
          "type": "word",
          "character": "카르프",
          "leftImage": "hue",
          "rightImage": "karf",
          "count": 4,
          "speech": [
            "그렇다고도 볼 수 있지...?",
            "그런데 난 집안 행사를 어려워했어.",
            "너무 정신없고 사람들이 많은 장소는 긴장이 되어서...",
            "파티 도중에 몰래 빠져나와 서재로 가곤 했어."
          ]
        },
        {
          "type": "word",
          "character": "휴",
          "leftImage": "hue",
          "rightImage": "karf",
          "count": 3,
          "speech": [
            "카르프는 책을 좋아하니까 서재에서 보내는 크리스마스도 즐거웠을 것 같아요..",
            "카르프다운 크리스마스라고 생각해요. 카르프는 책을 소중히 여기잖아요?",
            "소중한 책과 같이 크리스마스를 보낸거죠!"
          ]
        },
        {
          "type": "word",
          "character": "카르프",
          "leftImage": "hue",
          "rightImage": "karf",
          "count": 5,
          "speech": [
            "맞아.",
            "...",
            "나도 그렇게 생각했었는데,",
            "파티에서 몰래 빠져나와 서재에서 밤을 새거나 책을 읽다 잠들었어.",
            "파티날은 오전부터 분주하게 활동해서 피곤했거든.",
            "그런데 일어나면 항상 내방에서 일어났어."
          ]
        },
        {
          "type": "word",
          "character": "휴",
          "leftImage": "hue",
          "rightImage": "karf",
          "count": 1,
          "speech": ["누군가 방으로 옮겨준걸까요?"]
        },
        {
          "type": "word",
          "character": "카르프",
          "leftImage": "hue",
          "rightImage": "karf",
          "count": 5,
          "speech": [
            "응. 나도 그래서 사용인이 발견해서 옮겨주거나 내가 졸린상태로 무의식적으로 방을 찾아갔구나 생각했었어.",
            "그런데 언젠가 자다 깬 적이 있는데 아버지가 나를 옮겨주고 있던 중이었던거야.",
            "그때야서 뒤늦게 알아버린거야.",
            "가족들도 내가 어디로 갔는지 다 알고 있었다는걸.",
            "그렇지만 모른척 해주신거겠지."
          ]
        },
        {
          "type": "word",
          "character": "휴",
          "leftImage": "hue",
          "rightImage": "karf",
          "count": 2,
          "speech": [
            "다정한 가족들과 크리스마스를 보냈었네요.",
            "그 뒤로는 다시 가족들과 같이 크리스마스를 보냈나요?"
          ]
        },
        {
          "type": "word",
          "character": "카르프",
          "leftImage": "hue",
          "rightImage": "karf",
          "count": 8,
          "speech": [
            "음, 아니.",
            "그 뒤로는 학교에 갈 나이가 되어서 가족 파티에 참석하기 힘들었어.",
            "학생들 대부분이 크리스마스 기간에 교내에서 크리스마스를 보냈거든 물론 나도 학교에 남아있었고.",
            "아마 대부분이 학교에서 열어주는 파티를 참석하기 위해서 남은거겠지만,",
            "나는 내 연구실에서 보냈어.",
            "원래 사교행사에 잘안나기도 했고, 차라리 연구을 하는게 더 좋았으니까.",
            "그냥, 연구하고 공부하고 평소와 같았어.",
            "그래서 딱히 말해줄게 없어. 시시하게 보냈으니까."
          ]
        },
        {
          "type": "word",
          "character": "휴",
          "leftImage": "hue",
          "rightImage": "karf",
          "count": 2,
          "speech": [
            "예전에 마법학교에서 몇년이나 오래 보냈다고 말해줬잖아요.",
            "그동안 한번도 참여하지 않은 건가요?"
          ]
        },
        {
          "type": "word",
          "character": "카르프",
          "leftImage": "hue",
          "rightImage": "karf",
          "count": 2,
          "speech": [
            "음... 한번도 가지않은건 아니야.",
            "1학년이랑 마지막 8학년때는 참가했어."
          ]
        },
        {
          "type": "word",
          "character": "휴",
          "leftImage": "hue",
          "rightImage": "karf",
          "count": 3,
          "speech": [
            "!",
            "학교 크리스마스 파티는 어땠나요?",
            "엄청 멋있었을 것 같아요. 학교잖아요!"
          ]
        },
        {
          "type": "word",
          "character": "카르프",
          "leftImage": "hue",
          "rightImage": "karf",
          "count": 4,
          "speech": [
            "크게 특별할 것 없는 그냥 파티야.",
            "...음, 너는 지금 전혀 기억이 없어서 이렇게 말해도 이해하기 어려울려나",
            "교내 크리스마스 연회는 성 전체를 파티장으로 이용했는데 크기가...",
            "넓이로만 계산하자면 지금 우리집 팔십 배 정도 더 크다고 생각하면 될거야."
          ]
        },
        {
          "type": "word",
          "character": "휴",
          "leftImage": "hue",
          "rightImage": "karf",
          "count": 4,
          "speech": [
            "헉 그렇게 큰집이 있을 수 있나요?!",
            "파티장은 엄청난 곳이네요!",
            "(계속 물어보면 파티에 대한 힌트도 얻어 낼 수 있을 것 같아요!)",
            "더 자세히 이야기해 줄 수 있을까요?"
          ]
        },
        {
          "type": "word",
          "character": "카르프",
          "leftImage": "hue",
          "rightImage": "karf",
          "count": 6,
          "speech": [
            "자세히...?",
            "음... 너는 지금 기억이 없으니까 어떻게 설명해야하지.. 최대한 자세히 말해줄께.",
            "파티장엔 학생들이 의복을 화려하게 차려 입고 모여, 음... 행사에 대한 예의라고 생각하면 될거야.",
            "그리고 무대에는 오케스트라.. 그러니까 음악대가 파티가 끝날때까지 연주를 계속해.",
            "그 음악에 맞춰 홀 한가운데에서 두 명씩 짝을 맞춰 춤을 추기도 하고,",
            "한쪽으로는 간단하게 식사를 할 수 있는 디저트와 음료가 준비되어 있어서 거기서 쉬기도해."
          ]
        },
        {
          "type": "word",
          "character": "휴",
          "leftImage": "hue",
          "rightImage": "karf",
          "count": 2,
          "speech": ["말만 들어도 너무 멋져요.", "카르프는 파티에서 무얼 했나요?"]
        },
        {
          "type": "word",
          "character": "카르프",
          "leftImage": "hue",
          "rightImage": "karf",
          "count": 2,
          "speech": ["...", "... 같이..."]
        },
        {
          "type": "word",
          "character": "휴",
          "leftImage": "hue",
          "rightImage": "karf",
          "count": 2,
          "speech": ["?", "네?"]
        },
        {
          "type": "word",
          "character": "카르프",
          "leftImage": "hue",
          "rightImage": "karf",
          "count": 3,
          "speech": ["...", "...", "우리 같이 갔었어. 크리스마스 파티에"]
        },
        {
          "type": "word",
          "character": "휴",
          "leftImage": "hue",
          "rightImage": "karf",
          "count": 1,
          "speech": ["..."]
        },
        {
          "type": "word",
          "character": "카르프",
          "leftImage": "hue",
          "rightImage": "karf",
          "count": 3,
          "speech": [
            "네가 같이 가자해서 갔었어.",
            "나는 가기 싫다 매년 거절했지만, 네가 이제 졸업이니 마지막이니까 같이 가자고 해서...",
            "기억.. 나지않지?"
          ]
        },
        {
          "type": "word",
          "character": "휴",
          "leftImage": "hue",
          "rightImage": "karf",
          "count": 2,
          "speech": ["...", "미안해요 카르프."]
        },
        {
          "type": "word",
          "character": "카르프",
          "leftImage": "hue",
          "rightImage": "karf",
          "count": 3,
          "speech": [
            "...아니, 아니야.",
            "네가 사과해야할게 아니야.",
            "미안해. 또 부담스럽게 만들어 버렸어."
          ]
        },
        {
          "type": "word",
          "character": "휴",
          "leftImage": "hue",
          "rightImage": "karf",
          "count": 3,
          "speech": [
            "아니예요.",
            "괜히 떼써서 미안해요 카르프...",
            "저야말로 카르프를 힘들게 할 생각은 아니였어요"
          ]
        },
        {
          "type": "word",
          "character": "카르프",
          "leftImage": "hue",
          "rightImage": "karf",
          "count": 3,
          "speech": [
            "내 크리스마스에 대한 이야기는 이게 전부야.",
            "이제 크리스마스에 대한 이야기는 끝.",
            "정말 더 없어."
          ]
        },
        {
          "type": "word",
          "character": "휴",
          "leftImage": "hue",
          "rightImage": "karf",
          "count": 3,
          "speech": [
            "고마워요 카르프.",
            "카르프의 추억에 대해 더 알아갈 수 있어서 좋았어요.",
            "…! 아!"
          ]
        },
        {
          "type": "word",
          "character": "카르프",
          "leftImage": "hue",
          "rightImage": "karf",
          "count": 1,
          "speech": ["?"]
        },
        {
          "type": "word",
          "character": "휴",
          "leftImage": "hue",
          "rightImage": "karf",
          "count": 3,
          "speech": [
            "그러고보니 정작 휠라가 준 선물포장을 뜯지 않았어요.",
            "같이 선물을 열어봐요!",
            "휠라가 준 선물이 정말 궁금해요!"
          ]
        },
        {
          "type": "word",
          "character": "카르프",
          "leftImage": "hue",
          "rightImage": "karf",
          "count": 1,
          "speech": ["크리스마스 선물인데 벌써 열어보게?"]
        },
        {
          "type": "word",
          "character": "휴",
          "leftImage": "hue",
          "rightImage": "karf",
          "count": 1,
          "speech": ["크리스마스때 열어야하는 건가요?"]
        },
        {
          "type": "word",
          "character": "카르프",
          "leftImage": "hue",
          "rightImage": "karf",
          "count": 1,
          "speech": ["보통은 그렇지... 하지만 꼭 그렇지 않아도 괜찮긴해."]
        },
        {
          "type": "word",
          "character": "휴",
          "leftImage": "hue",
          "rightImage": "karf",
          "count": 5,
          "speech": [
            "헉, 그럼 크리스마스때 열래요!",
            "히히, 카르프 말고 선물은 처음이라 너무 기대되어요!",
            "휠라는 정말 세심하고 상냥해요.",
            "저희가 선물을 준비하지 않다는걸 예상했다고 하면서 이렇게 챙겨주었어요.",
            "정말 좋은 친구예요. 계속 친하게 지내고 싶어요."
          ]
        },
        {
          "type": "word",
          "character": "카르프",
          "leftImage": "hue",
          "rightImage": "karf",
          "count": 2,
          "speech": ["...", "그건... 아마 힘들거야."]
        },
        {
          "type": "word",
          "character": "휴",
          "leftImage": "hue",
          "rightImage": "karf",
          "count": 1,
          "speech": ["네..?"]
        },
        {
          "type": "word",
          "character": "카르프",
          "leftImage": "hue",
          "rightImage": "karf",
          "count": 4,
          "speech": [
            "지금까지는 괜찮아. 응, 의뢰인과 배달원의 사이까지는.",
            "하지만 더 가까워지면 안돼. 어느 순간 방심해버려서 다 들켜버릴지 몰라.",
            "사실 지금도 조금 위험하지만..",
            "여기서 더 의심을 심어주게되면 어떤일로 되돌아올지 모르니 조심해야해."
          ]
        },
        {
          "type": "word",
          "character": "휴",
          "leftImage": "hue",
          "rightImage": "karf",
          "count": 1,
          "speech": ["하지만 휠라는 다정한걸요. 이해해줄지도 몰라요."]
        },
        {
          "type": "word",
          "character": "카르프",
          "leftImage": "hue",
          "rightImage": "karf",
          "count": 2,
          "speech": [
            "휠라가 다정하다는건 알아.",
            "하지만 그것과 조금.. 다른 문제야."
          ]
        },
        {
          "type": "word",
          "character": "휴",
          "leftImage": "hue",
          "rightImage": "karf",
          "count": 1,
          "speech": ["카르프..."]
        },
        {
          "type": "word",
          "character": "카르프",
          "leftImage": "hue",
          "rightImage": "karf",
          "count": 6,
          "speech": [
            "그치만 괜찮아..!",
            "모두 해결할 수 있어.",
            "실험만 성공하고 너의 기억만 돌아온다면 하나씩 해결할 수 있는 문제들이야!",
            "지금 영혼과 기억의 연결과 신체의 재활성화가 제일 큰 문제인데 이번에 찾은 가설에 의하면......",
            "영혼에는 오류가 없는데 반해 기억이 제대로 복구되지 않은 문제에서 영혼의 재구축과 기억의 복구의 상관관계에서 내가 잘못 계산하고 있는.....",
            "그리고 신체의 나이를 추정하는데 내가 잘못 가정하고 있을 수 있어서 이번 실험에서는 신체 나이를 배제하여......"
          ]
        },
        {
          "type": "word",
          "character": "휴",
          "leftImage": "hue",
          "rightImage": "karf",
          "count": 1,
          "speech": ["..."]
        },
        {
          "type": "word",
          "character": "카르프",
          "leftImage": "hue",
          "rightImage": "karf",
          "count": 3,
          "speech": [
            "...그래서 이번 실험은 지금까지 실험을 모두 새로 가정해서 공식부터 다시 만들었어. 가장 성공확률이 높아.",
            "지금 막 실험 준비를 하려고 미리 알려주려고 나온거야.",
            "오늘 저녁부터 시작할거야. ...혹시 할일이 있었다면 내일이라던가 조정할께."
          ]
        },
        {
          "type": "word",
          "character": "휴",
          "leftImage": "hue",
          "rightImage": "karf",
          "count": 1,
          "speech": ["오늘 저녁이요? 빨리 시작하네요!"]
        },
        {
          "type": "word",
          "character": "카르프",
          "leftImage": "hue",
          "rightImage": "karf",
          "count": 6,
          "speech": [
            "...내가 너무 오래 끝내지 못했으니까.",
            "적어도 올해안에는 되돌려주고 싶었어.",
            "이번에는 느낌이 좋아. 테스트들도 괜찮은 성공률을 보였거든!",
            "…그러니까 이번 실험이 성공하면 모두 해결할 수 있어.",
            "성공하면 이제 하고싶은거 모두 할 수 있어. 휠라와도 그때 친해지면 되.",
            "휠라는 기다려줄거야. ...아마도."
          ]
        },
        {
          "type": "word",
          "character": "휴",
          "leftImage": "hue",
          "rightImage": "karf",
          "count": 1,
          "speech": ["정말 그런가요?"]
        },
        {
          "type": "word",
          "character": "카르프",
          "leftImage": "hue",
          "rightImage": "karf",
          "count": 2,
          "speech": [
            "…응 너는 가능할거야.",
            "너는 어디서든 사람들과 쉽게 어울리고 친해졌으니까."
          ]
        },
        {
          "type": "word",
          "character": "휴",
          "leftImage": "hue",
          "rightImage": "karf",
          "count": 12,
          "speech": [
            "...",
            "(종종 카르프는 ‘과거의 저’를 과대평가하고 있다는 생각이 들어요.)",
            "(제게 ‘과거의 저’에 대한 기억은 없지만요.)",
            "(가끔 그런 생각이 들어요.)",
            "(‘과거의 저’는 어떤 사람이었을까요?)",
            "(카르프가 했던 말들을 생각하면 무척이나 상냥하고 다재다능하고 능숙한 사람처럼 들려요)",
            "(그런 완벽한 사람이기에 카르프가 그리워하는걸까.)",
            "(가끔 이런 의문이 머리를 스쳐 지나가요.)",
            "(제가 기억이 돌아오지 않으면 어떻게 될까하고요)",
            "(저를 ‘휴’라고 부를 수 있을까요?)",
            "(카르프는 저를 계속 ‘휴’라고 불러줄까요?)",
            "(‘휴’가 아닌 저는 뭐일까요?)"
          ]
        },
        {
          "type": "word",
          "character": "카르프",
          "leftImage": "hue",
          "rightImage": "karf",
          "count": 2,
          "speech": ["... 사담이 너무 길어졌네. 슬슬 실험준비를 해야할 것 같아", "이번엔 조금 길어질거야."]
        },
        {
          "type": "word",
          "character": "휴",
          "leftImage": "hue",
          "rightImage": "karf",
          "count": 1,
          "speech": ["얼마나 오래 걸리나요?"]
        },
        {
          "type": "word",
          "character": "카르프",
          "leftImage": "hue",
          "rightImage": "karf",
          "count": 1,
          "speech": ["음, 3일... 더 걸릴 수도 있어."]
        },
        {
          "type": "word",
          "character": "휴",
          "leftImage": "hue",
          "rightImage": "karf",
          "count": 1,
          "speech": ["앗. 안돼요!"]
        },
        {
          "type": "word",
          "character": "카르프",
          "leftImage": "hue",
          "rightImage": "karf",
          "count": 2,
          "speech": ["?", "일정이 있었어?"]
        },
        {
          "type": "word",
          "character": "휴",
          "leftImage": "hue",
          "rightImage": "karf",
          "count": 5,
          "speech": [
            "아, 아니 그러니까",
            "(크리스마스가 25일, 오늘이 20일이니까 3일이나 준비할 시간이 없어졌어요!)",
            "(크리스마스 준비를 하루동안 할 수 있을까요?)",
            "(최선을 다 할 수 밖에 없네요..! 우선 깜짝파티니까 계속 비밀로 해야해요.)",
            "그.. 일정은 없지만 3일이나 계속 실험을 이어가면 그동안 카르프 안잘거잖아요? 오래 밤새면 안좋다는 이야기였어요!"
          ]
        },
        {
          "type": "word",
          "character": "카르프",
          "leftImage": "hue",
          "rightImage": "karf",
          "count": 2,
          "speech": ["…응 그래. 고마워.", "너무 길어지지 않도록 노력해볼께."]
        },
        {
          "type": "word",
          "character": "휴",
          "leftImage": "hue",
          "rightImage": "karf",
          "count": 3,
          "speech": [
            "(그건 안자겠다는 말이잖아요...)",
            "(하지만 다행이에요. 파티계획을 들키지 않은것 같아요.)",
            "네!"
          ]
        },
        {
          "type": "word",
          "character": "카르프",
          "leftImage": "hue",
          "rightImage": "karf",
          "count": 2,
          "speech": [
            "난 창고에서 가져갈 약품이 있어.",
            "약품 찾는데 좀 시간이 걸릴 수 있으니까 먼저 실험실 침대에 누워있어."
          ]
        },
        {
          "type": "word",
          "character": "휴",
          "leftImage": "hue",
          "rightImage": "karf",
          "count": 1,
          "speech": ["알겠어요."]
        },
        {
          "type": "word",
          "character": "카르프",
          "leftImage": "hue",
          "rightImage": "karf",
          "count": 1,
          "speech": [
            "... 그 인형은 다 고쳐서 내 방에 있으니까 가져가도 괜찮아.",
            "방안에 있는 물건들 만지지마. 인형만 가져가야해?",
            "...그럼 들어가 있어."
          ]
        },
        {
          "type": "word",
          "character": "휴",
          "leftImage": "hue",
          "rightImage": "karf",
          "count": 1,
          "speech": ["!"]
        },
        {
          "type": "word",
          "character": "",
          "leftImage": null,
          "rightImage": null,
          "count": 1,
          "speech": ["(타닥타닥)"]
        },
        {
          "type": "word",
          "character": "휴",
          "leftImage": "hue",
          "rightImage": null,
          "count": 5,
          "speech": [
            "(카르프가 인형을 생각해줄지 몰랐어요!)",
            "(인형은 예전에 휠라가 준 인형인데, 제가 망가트려서 카르프가 고쳐준다고 가져갔었어요.)",
            "(조금 시간이 걸려서 잊고 있었는데... 카르프가 다 고쳤나봐요!)",
            "(카르프도 정말 다정해요. 제가 실험때마다 안고있던걸 기억해줬네요.)",
            "(그럼 인형을 먼저 가지러 카르프의 방으로 가야겠어요.)"
          ]
        },
        {
          "type": "word",
          "character": "",
          "leftImage": null,
          "rightImage": null,
          "count": 1,
          "speech": ["(끼이익)"]
        },
        {
          "type": "word",
          "character": "휴",
          "leftImage": "hue",
          "rightImage": null,
          "count": 7,
          "speech": [
            "(와아...)",
            "(카르프방은 정말 오랜만인데... 너무 방을 어질러놓았어요!)",
            "(이런 환경에서 어떻게 연구를 하는걸까요?)",
            "(꼭 다른 물건은 만지지 말라했으니까 청소하면 안돼겠죠?)",
            "(저번에는 이렇게까지 어지럽지 않았는데...)",
            "(그나저나 인형이 어디있을지 방안을 찾아봐야할 것 같아요.)",
            "(실험도구가 그대로 어질러있어서 조금 어려울것 같지만 힘내볼께요!)"
          ]
        }
      ]
    }
  ]
}
